linear_inverse_model/CSLIM.py
linear_inverse_model/LIM_utils.py
linear_inverse_model/STLIM.py
linear_inverse_model/__init__.py
linear_inverse_model-0.1.1.dist-info/METADATA
linear_inverse_model-0.1.1.dist-info/WHEEL
linear_inverse_model-0.1.1.dist-info/licenses/LICENSE
linear_inverse_model-0.1.1.dist-info/RECORD
