Metadata-Version: 2.4
Name: linear-inverse-model
Version: 0.1.1
Summary: Linear Inverse Model (LIM) toolbox
Project-URL: Homepage, https://github.com/WANGYuxinCi/linear-inverse-model
Project-URL: Issues, https://github.com/WANGYuxinCi/linear-inverse-model/issues
Author: Yuxin Wang
License: Attribution 4.0 International
License-File: LICENSE
Requires-Python: >=3.9
Requires-Dist: netcdf4>=1.6
Requires-Dist: numpy>=1.23
Requires-Dist: pandas>=1.5
Requires-Dist: scipy>=1.10
Requires-Dist: statsmodels>=0.13
Requires-Dist: xarray>=2023.1
Provides-Extra: dask
Requires-Dist: bottleneck>=1.3; extra == 'dask'
Requires-Dist: dask>=2023.1; extra == 'dask'
Provides-Extra: maps
Requires-Dist: cartopy>=0.22; extra == 'maps'
Requires-Dist: cftime>=1.6; extra == 'maps'
Provides-Extra: speed
Requires-Dist: numba>=0.58; extra == 'speed'
Provides-Extra: viz
Requires-Dist: matplotlib>=3.6; extra == 'viz'
